tara/__init__.py
tara/__main__.py
tara/template.py
tara-0.1.0.dist-info/AUTHORS
tara-0.1.0.dist-info/LICENSE
tara-0.1.0.dist-info/METADATA
tara-0.1.0.dist-info/WHEEL
tara-0.1.0.dist-info/entry_points.txt
tara-0.1.0.dist-info/top_level.txt
tara-0.1.0.dist-info/RECORD
