Metadata-Version: 2.1
Name: tara
Version: 0.1.0
Summary: Tara Python Wrapper
Home-page: https://github.com/ekpyrosis/tara
Author: Sinan Alioglu
Author-email: sinan@alioglu.org
License: 3-clause BSD
Keywords: tara
Platform: any
Classifier: Development Status :: 1 - Planning
Classifier: Programming Language :: Python
Classifier: Programming Language :: Python :: 3
Classifier: Programming Language :: Python :: 3.5
Classifier: Programming Language :: Python :: 3.6
Classifier: Programming Language :: Python :: 3.7
Classifier: Programming Language :: Python :: 3.8
